pyamit/__init__.py
pyamit/main.py
pyamit-0.1.3.dist-info/METADATA
pyamit-0.1.3.dist-info/WHEEL
pyamit-0.1.3.dist-info/entry_points.txt
pyamit-0.1.3.dist-info/licenses/LICENSE
pyamit-0.1.3.dist-info/RECORD
