Metadata-Version: 2.4
Name: pyamit
Version: 0.1.3
Summary: A fast Python CLI tool for formatting and sorting YAML files with pre-commit integration
Project-URL: Homepage, https://github.com/mounirmesselmeni/pyamit
Project-URL: Repository, https://github.com/mounirmesselmeni/pyamit
Project-URL: Issues, https://github.com/mounirmesselmeni/pyamit/issues
Project-URL: Documentation, https://github.com/mounirmesselmeni/pyamit#readme
Author-email: Mounir Messelmeni <messelmeni.mounir@gmail.com>
Maintainer-email: Mounir Messelmeni <messelmeni.mounir@gmail.com>
License: MIT
License-File: LICENSE
Keywords: cli,formatter,linting,pre-commit,python,yaml
Classifier: Development Status :: 4 - Beta
Classifier: Intended Audience :: Developers
Classifier: License :: OSI Approved :: MIT License
Classifier: Operating System :: OS Independent
Classifier: Programming Language :: Python :: 3
Classifier: Programming Language :: Python :: 3.11
Classifier: Programming Language :: Python :: 3.12
Classifier: Programming Language :: Python :: 3.13
Classifier: Topic :: Software Development :: Quality Assurance
Classifier: Topic :: Text Processing :: General
Classifier: Topic :: Utilities
Requires-Python: >=3.11
Requires-Dist: pytest>=8.4.2
Requires-Dist: pyyaml>=6.0.3
Requires-Dist: typer>=0.19.2
